dronekit/__init__.py
dronekit/lib.py
dronekit/mavlink.py
dronekit/util.py
dronekit/cloud/CloudClient.py
dronekit/cloud/__init__.py
dronekit/test/__init__.py
dronekit/test/sitl/__init__.py
dronekit/test/sitl/test_110.py
dronekit/test/sitl/test_115.py
dronekit/test/sitl/test_12.py
dronekit/test/sitl/test_capability_and_version.py
dronekit/test/sitl/test_channels.py
dronekit/test/sitl/test_earlyattrs.py
dronekit/test/sitl/test_errprinter.py
dronekit/test/sitl/test_goto.py
dronekit/test/sitl/test_locations.py
dronekit/test/sitl/test_mavlink.py
dronekit/test/sitl/test_mode_settings.py
dronekit/test/sitl/test_modeavailable.py
dronekit/test/sitl/test_parameters.py
dronekit/test/sitl/test_reboot.py
dronekit/test/sitl/test_sensor_calibration.py
dronekit/test/sitl/test_simpledemo.py
dronekit/test/sitl/test_state.py
dronekit/test/sitl/test_timeout.py
dronekit/test/sitl/test_vehicleclass.py
dronekit/test/sitl/test_waypoints.py
dronekit/test/unit/__init__.py
dronekit/test/unit/test_api.py
dronekit-2.9.2.dist-info/LICENSE
dronekit-2.9.2.dist-info/METADATA
dronekit-2.9.2.dist-info/WHEEL
dronekit-2.9.2.dist-info/top_level.txt
dronekit-2.9.2.dist-info/zip-safe
dronekit-2.9.2.dist-info/RECORD
